codeball/__init__.py
codeball/codeball_frames.py
codeball/game_dataset.py
codeball/tactical.py
codeball/visualizations.py
codeball/patterns/__init__.py
codeball/patterns/passes_into_the_box.py
codeball/patterns/patterns.py
codeball/patterns/set_pieces.py
codeball/patterns/team_stretched.py
codeball/tests/__init__.py
codeball/tests/test_models.py
codeball/tests/test_patterns.py
codeball/tests/test_visualizations.py
codeball/utils/__init__.py
codeball/utils/json_encoders.py
codeball-0.3.1.dist-info/LICENSE
codeball-0.3.1.dist-info/METADATA
codeball-0.3.1.dist-info/WHEEL
codeball-0.3.1.dist-info/top_level.txt
codeball-0.3.1.dist-info/RECORD
