Metadata-Version: 2.1
Name: codeball
Version: 0.3.1
Summary: Data driven tactical and video analysis of soccer games
Home-page: https://github.com/metrica-sports/codeball
Author: Bruno Dagnino
Author-email: bruno@metrica-sports.com
License: UNKNOWN
Platform: UNKNOWN
Classifier: Development Status :: 3 - Alpha
Classifier: Intended Audience :: Developers
Classifier: Intended Audience :: Science/Research
Classifier: Programming Language :: Python :: 3
Classifier: Programming Language :: Python :: 3.7
Classifier: Programming Language :: Python :: 3.8
Classifier: License :: OSI Approved :: MIT License
Classifier: Topic :: Scientific/Engineering
Requires-Python: >=3.7, <4
Requires-Dist: kloppy (==1.7.0)
Requires-Dist: pandas (>=1.0.5)
Provides-Extra: development
Requires-Dist: pre-commit ; extra == 'development'
Provides-Extra: test
Requires-Dist: pytest ; extra == 'test'
